README.rst
crowd.py
setup.py
CrowdEvry.egg-info/PKG-INFO
CrowdEvry.egg-info/SOURCES.txt
CrowdEvry.egg-info/dependency_links.txt
CrowdEvry.egg-info/requires.txt
CrowdEvry.egg-info/top_level.txt